README.rst
setup.py
HolaMundo/Dragon.py
HolaMundo/__init__.py
HolaMundoDragon.egg-info/PKG-INFO
HolaMundoDragon.egg-info/SOURCES.txt
HolaMundoDragon.egg-info/dependency_links.txt
HolaMundoDragon.egg-info/entry_points.txt
HolaMundoDragon.egg-info/requires.txt
HolaMundoDragon.egg-info/top_level.txt