Metadata-Version: 2.1
Name: HolaMundoDragon
Version: 2.0.0
Summary: Aprende IT package example
Home-page: https://chupalo.com
Author: El dragon
Author-email: un_email@gmail.com
License: NOTFOUND
Download-URL: https://URL_PAQUETE/ejemplo_paquete/-/archive/master/ejemplo_paquete-master.tar
Keywords: HolaMundoDragon,ejemplo,paquete,package,example
Platform: UNKNOWN
Classifier: Development Status :: 4 - Beta
Classifier: Intended Audience :: Developers
Classifier: Topic :: Software Development :: Build Tools
Classifier: Programming Language :: Python :: 2.7
Classifier: Programming Language :: Python :: 3.4
Classifier: Programming Language :: Python :: 3.5
Classifier: Programming Language :: Python :: 3.6
Classifier: Programming Language :: Python :: 3.7
